nj_lab01/__init__.py
nj_lab01/main.py
nj_lab01-1.4.data/scripts/say-hello-cyb600
nj_lab01-1.4.dist-info/METADATA
nj_lab01-1.4.dist-info/WHEEL
nj_lab01-1.4.dist-info/entry_points.txt
nj_lab01-1.4.dist-info/top_level.txt
nj_lab01-1.4.dist-info/RECORD
