Metadata-Version: 2.1
Name: nj_lab01
Version: 1.4
Author: Nsundidi Jorge
Author-email: jorgen@canisius.edu
License: Apache License Version 2.0
